htmlx/JSON.py
htmlx/__init__.py
htmlx/__main__.py
htmlx/decorators.py
htmlx/dom.py
htmlx/events.py
htmlx/style.py
htmlx/svg.py
htmlx/tags.py
htmlx/utils.py
htmlx/geom/__init__.py
htmlx/geom/vec2.py
htmlx/geom/vec3.py
htmlx/i18n/__init__.py
htmlx/i18n/ar/__init__.py
htmlx/i18n/ch/__init__.py
htmlx/i18n/da/__init__.py
htmlx/i18n/de/__init__.py
htmlx/i18n/es/__init__.py
htmlx/i18n/fr/__init__.py
htmlx/i18n/hi/__init__.py
htmlx/i18n/it/__init__.py
htmlx/i18n/mi/__init__.py
htmlx/i18n/ru/__init__.py
htmlx/i18n/sw/__init__.py
htmlx/i18n/zu/__init__.py
htmlx/parsers/__init__.py
htmlx/parsers/expatbuilder.py
htmlx/webapi/__init__.py
htmlx/webapi/console.py
htmlx/webapi/encoding.py
htmlx/webapi/fetch.py
htmlx/webapi/geo.py
htmlx/webapi/history.py
htmlx/webapi/url.py
htmlx/webapi/urlpattern.py
htmlx/webapi/websocket.py
htmlx/webapi/webstorage.py
htmlx/webapi/webworkers.py
htmlx/webapi/xhr.py
htmlx/webapi/xpath.py
htmlx/xml/__init__.py
htmlx/xml/aframe.py
htmlx/xml/mathml.py
htmlx/xml/sitemap.py
htmlx/xml/x3d.py
htmlx-0.0.3.dist-info/LICENSE.txt
htmlx-0.0.3.dist-info/METADATA
htmlx-0.0.3.dist-info/WHEEL
htmlx-0.0.3.dist-info/entry_points.txt
htmlx-0.0.3.dist-info/top_level.txt
htmlx-0.0.3.dist-info/RECORD
