Metadata-Version: 2.1
Name: htmlx
Version: 0.0.3
Summary: Generate html with python 3
Home-page: https://github.com/byteface/htmlx
Author: @byteface
Author-email: byteface@gmail.com
License: MIT
Download-URL: https://github.com/byteface/htmlx/archive/0.0.3 .tar.gz
Keywords: html,generate,templating,dom,vdom,json,web,template,DOM,GUI,render,website,apps,html5,SVG,x3d,events,geom
Platform: UNKNOWN
Classifier: Programming Language :: Python :: 3
Classifier: Programming Language :: JavaScript
Classifier: Programming Language :: Python
Classifier: Programming Language :: Python :: 3.6
Classifier: Programming Language :: Python :: 3.7
Classifier: Programming Language :: Python :: 3.8
Classifier: Programming Language :: Python :: 3.9
Classifier: Programming Language :: Python :: 3.10
Classifier: Development Status :: 4 - Beta
Classifier: Environment :: Web Environment
Classifier: Intended Audience :: Developers
Classifier: Intended Audience :: Other Audience
Classifier: License :: OSI Approved :: MIT License
Classifier: Natural Language :: English
Classifier: Operating System :: OS Independent
Classifier: Topic :: Internet
Classifier: Topic :: Internet :: WWW/HTTP
Classifier: Topic :: Multimedia :: Graphics :: Presentation
Classifier: Topic :: Software Development
Classifier: Topic :: Software Development :: Code Generators
Classifier: Topic :: Terminals
Classifier: Topic :: Utilities
Classifier: Topic :: Internet :: WWW/HTTP :: Dynamic Content
Classifier: Topic :: Software Development :: Libraries :: Python Modules
Classifier: Topic :: Text Processing :: Markup :: HTML
Requires-Python: >=3.6
License-File: LICENSE.txt
Requires-Dist: urllib3 (~=1.26.7)
